dall_e/__init__.py
dall_e/decoder.py
dall_e/encoder.py
dall_e/utils.py
DALL_E-0.1.dist-info/LICENSE
DALL_E-0.1.dist-info/METADATA
DALL_E-0.1.dist-info/WHEEL
DALL_E-0.1.dist-info/top_level.txt
DALL_E-0.1.dist-info/zip-safe
DALL_E-0.1.dist-info/RECORD
